weave/LICENSE.txt
weave/__init__.py
weave/_dumb_shelve.py
weave/_dumbdbm_patched.py
weave/accelerate_tools.py
weave/ast_tools.py
weave/base_info.py
weave/base_spec.py
weave/blitz_spec.py
weave/blitz_tools.py
weave/build_tools.py
weave/bytecodecompiler.py
weave/c_spec.py
weave/catalog.py
weave/common_info.py
weave/converters.py
weave/cpp_namespace_spec.py
weave/ext_tools.py
weave/inline_tools.py
weave/numpy_scalar_spec.py
weave/platform_info.py
weave/setup.py
weave/size_check.py
weave/slice_handler.py
weave/standard_array_spec.py
weave/swig2_spec.py
weave/swigptr.py
weave/swigptr2.py
weave/version.py
weave/vtk_spec.py
weave/blitz/blitz/Makefile.am
weave/blitz/blitz/Makefile.in
weave/blitz/blitz/README
weave/blitz/blitz/applics.h
weave/blitz/blitz/array-impl.h
weave/blitz/blitz/array-old.h
weave/blitz/blitz/array.h
weave/blitz/blitz/bench.cc
weave/blitz/blitz/bench.h
weave/blitz/blitz/benchext.cc
weave/blitz/blitz/benchext.h
weave/blitz/blitz/blitz.h
weave/blitz/blitz/bzconfig.h
weave/blitz/blitz/bzdebug.h
weave/blitz/blitz/compiler.h
weave/blitz/blitz/config.h.in
weave/blitz/blitz/etbase.h
weave/blitz/blitz/extremum.h
weave/blitz/blitz/funcs.h
weave/blitz/blitz/indexexpr.h
weave/blitz/blitz/limits-hack.h
weave/blitz/blitz/listinit.h
weave/blitz/blitz/matbops.h
weave/blitz/blitz/matdiag.h
weave/blitz/blitz/matexpr.h
weave/blitz/blitz/matgen.h
weave/blitz/blitz/mathf2.h
weave/blitz/blitz/mathfunc.h
weave/blitz/blitz/matltri.h
weave/blitz/blitz/matref.h
weave/blitz/blitz/matrix.cc
weave/blitz/blitz/matrix.h
weave/blitz/blitz/matsymm.h
weave/blitz/blitz/mattoep.h
weave/blitz/blitz/matuops.h
weave/blitz/blitz/matutri.h
weave/blitz/blitz/memblock.cc
weave/blitz/blitz/memblock.h
weave/blitz/blitz/minmax.h
weave/blitz/blitz/mstruct.h
weave/blitz/blitz/numinquire.h
weave/blitz/blitz/numtrait.h
weave/blitz/blitz/ops.h
weave/blitz/blitz/prettyprint.h
weave/blitz/blitz/promote-old.h
weave/blitz/blitz/promote.h
weave/blitz/blitz/rand-dunif.h
weave/blitz/blitz/rand-normal.h
scipy_weave-0.19.0.dist-info/LICENSE.txt
scipy_weave-0.19.0.dist-info/METADATA
scipy_weave-0.19.0.dist-info/WHEEL
scipy_weave-0.19.0.dist-info/top_level.txt
scipy_weave-0.19.0.dist-info/RECORD
