Metadata-Version: 2.1
Name: scipy-weave
Version: 0.19.0
Summary: scipy-weave: a C++ compiler for Python 2.
Home-page: http://www.github.com/scipy/weave
Maintainer: scipy-weave developers
Maintainer-email: scipy-dev@scipy.org
License: BSD
Download-URL: https://pypi.python.org/pypi/weave
Platform: Windows
Platform: Linux
Platform: Solaris
Platform: Mac OS-X
Platform: Unix
Classifier: Development Status :: 4 - Beta
Classifier: Intended Audience :: Science/Research
Classifier: Intended Audience :: Developers
Classifier: License :: OSI Approved
Classifier: Programming Language :: C
Classifier: Programming Language :: Python :: 3
Classifier: Topic :: Software Development
Classifier: Topic :: Scientific/Engineering
Classifier: Operating System :: Microsoft :: Windows
Classifier: Operating System :: POSIX
Classifier: Operating System :: Unix
Classifier: Operating System :: MacOS
Requires-Python: >=3.4,<3.10
License-File: LICENSE.txt
